<?xml version="1.0" encoding="utf-8"?>
<toc>
  <breadcrumbs>
    <li>
      <a href="854ccd60-6c3b-4754-1fee-cd46e85c309b.htm">Docs</a>
    </li>
    <li>
      <a href="854ccd60-6c3b-4754-1fee-cd46e85c309b.htm">Namespaces</a>
    </li>
    <li>
      <a href="a3b60ffe-d18c-97f8-7c1d-28d9f88eb206.htm">MFiles.<wbr />VAF.<wbr />Configuration</a>
    </li>
  </breadcrumbs>
  <tocItems>
    <li>
      <a id="56a49742-298a-d4c2-96f2-7bd50401d856" class="has-submenu" href="56a49742-298a-d4c2-96f2-7bd50401d856.htm">
        <span data-tocFile="../toc/IDAGA.xml" class="icon toggle" onclick="ToggleExpandCollapse(this); return false;">
          <i class="fa fa-angle-right"> </i>
        </span>Account<wbr />Helper</a>
      <ul class="toc-menu is-hidden"> </ul>
    </li>
    <li>
      <a id="a7a3de3e-a0ee-91ca-7f37-246be080a2e4" href="a7a3de3e-a0ee-91ca-7f37-246be080a2e4.htm">Account<wbr />Helper.<wbr />Resolve<wbr />Login<wbr />Account</a>
    </li>
    <li>
      <a id="c6af8418-76ce-6d81-976d-f081e1e0d0b2" class="has-submenu" href="c6af8418-76ce-6d81-976d-f081e1e0d0b2.htm">
        <span data-tocFile="../toc/IDCGA.xml" class="icon toggle" onclick="ToggleExpandCollapse(this); return false;">
          <i class="fa fa-angle-right"> </i>
        </span>Configuration<wbr />Storage<wbr />In<wbr />Vault</a>
      <ul class="toc-menu is-hidden"> </ul>
    </li>
    <li>
      <a id="315580af-5d9a-fd06-8391-5ea9a30e7390" href="315580af-5d9a-fd06-8391-5ea9a30e7390.htm">Configuration<wbr />Storage<wbr />In<wbr />Vault.<wbr />Configuration<wbr />IDCombining<wbr />Mode</a>
    </li>
    <li>
      <a id="3c782a86-a778-c0b5-6eb5-ac32ce309a8d" class="has-submenu" href="3c782a86-a778-c0b5-6eb5-ac32ce309a8d.htm">
        <span data-tocFile="../toc/IDEGA.xml" class="icon toggle" onclick="ToggleExpandCollapse(this); return false;">
          <i class="fa fa-angle-right"> </i>
        </span>Configuration<wbr />Storage<wbr />In<wbr />Vault.<wbr />Validating<wbr />Contract<wbr />Resolver</a>
      <ul class="toc-menu is-hidden"> </ul>
    </li>
    <li>
      <a id="42b10f0d-48fc-bd1d-9d43-47ee83016254" class="has-submenu" href="42b10f0d-48fc-bd1d-9d43-47ee83016254.htm">
        <span data-tocFile="../toc/IDFGA.xml" class="icon toggle" onclick="ToggleExpandCollapse(this); return false;">
          <i class="fa fa-angle-right"> </i>
        </span>Configuration<wbr />Storage<wbr />In<wbr />Vault.<wbr />Validating<wbr />Value<wbr />Provider</a>
      <ul class="toc-menu is-hidden"> </ul>
    </li>
    <li>
      <a id="b76a3935-2fa4-0b2e-e175-e37936610cdd" class="has-submenu" href="b76a3935-2fa4-0b2e-e175-e37936610cdd.htm">
        <span data-tocFile="../toc/IDGGA.xml" class="icon toggle" onclick="ToggleExpandCollapse(this); return false;">
          <i class="fa fa-angle-right"> </i>
        </span>Date<wbr />Time<wbr />Extensions</a>
      <ul class="toc-menu is-hidden"> </ul>
    </li>
    <li>
      <a id="2c167957-9bec-03b1-fa46-19320649fc11" class="has-submenu" href="2c167957-9bec-03b1-fa46-19320649fc11.htm">
        <span data-tocFile="../toc/IDHGA.xml" class="icon toggle" onclick="ToggleExpandCollapse(this); return false;">
          <i class="fa fa-angle-right"> </i>
        </span>Dynamic<wbr />Property<wbr />Value<wbr />Setter</a>
      <ul class="toc-menu is-hidden"> </ul>
    </li>
    <li>
      <a id="8c55564e-9209-17cf-2ee6-b9bf8727266a" class="has-submenu" href="8c55564e-9209-17cf-2ee6-b9bf8727266a.htm">
        <span data-tocFile="../toc/IDIGA.xml" class="icon toggle" onclick="ToggleExpandCollapse(this); return false;">
          <i class="fa fa-angle-right"> </i>
        </span>Enum<wbr />Option</a>
      <ul class="toc-menu is-hidden"> </ul>
    </li>
    <li>
      <a id="9b486ab3-f62a-fd27-3165-783a1adab53a" class="has-submenu" href="9b486ab3-f62a-fd27-3165-783a1adab53a.htm">
        <span data-tocFile="../toc/IDJGA.xml" class="icon toggle" onclick="ToggleExpandCollapse(this); return false;">
          <i class="fa fa-angle-right"> </i>
        </span>Exception<wbr />Extension<wbr />Methods</a>
      <ul class="toc-menu is-hidden"> </ul>
    </li>
    <li>
      <a id="d26d039b-50cb-9c0a-b088-ecccbe89ed1e" class="has-submenu" href="d26d039b-50cb-9c0a-b088-ecccbe89ed1e.htm">
        <span data-tocFile="../toc/IDKGA.xml" class="icon toggle" onclick="ToggleExpandCollapse(this); return false;">
          <i class="fa fa-angle-right"> </i>
        </span>Extended<wbr />Json<wbr />Conf<wbr />Editor<wbr />Attribute</a>
      <ul class="toc-menu is-hidden"> </ul>
    </li>
    <li>
      <a id="b958ad8a-7b0c-79b3-1509-5c5bd1db7a86" class="has-submenu" href="b958ad8a-7b0c-79b3-1509-5c5bd1db7a86.htm">
        <span data-tocFile="../toc/IDLGA.xml" class="icon toggle" onclick="ToggleExpandCollapse(this); return false;">
          <i class="fa fa-angle-right"> </i>
        </span>Group<wbr />Len<wbr />Limit</a>
      <ul class="toc-menu is-hidden"> </ul>
    </li>
    <li>
      <a id="429df8ff-1722-d2d4-635f-53f944006c0f" class="has-submenu" href="429df8ff-1722-d2d4-635f-53f944006c0f.htm">
        <span data-tocFile="../toc/IDMGA.xml" class="icon toggle" onclick="ToggleExpandCollapse(this); return false;">
          <i class="fa fa-angle-right"> </i>
        </span>IApplication<wbr />License<wbr />Content</a>
      <ul class="toc-menu is-hidden"> </ul>
    </li>
    <li>
      <a id="0fa4e205-b476-851b-4c23-b9c59070fda3" class="has-submenu" href="0fa4e205-b476-851b-4c23-b9c59070fda3.htm">
        <span data-tocFile="../toc/IDNGA.xml" class="icon toggle" onclick="ToggleExpandCollapse(this); return false;">
          <i class="fa fa-angle-right"> </i>
        </span>IConfiguration</a>
      <ul class="toc-menu is-hidden"> </ul>
    </li>
    <li>
      <a id="fd299750-25e7-20f0-edee-e2ec051f1d82" class="has-submenu" href="fd299750-25e7-20f0-edee-e2ec051f1d82.htm">
        <span data-tocFile="../toc/IDOGA.xml" class="icon toggle" onclick="ToggleExpandCollapse(this); return false;">
          <i class="fa fa-angle-right"> </i>
        </span>IConfiguration<wbr />Storage</a>
      <ul class="toc-menu is-hidden"> </ul>
    </li>
    <li>
      <a id="ffa90a83-90a3-801d-f2d6-e26b81fca6f4" class="has-submenu" href="ffa90a83-90a3-801d-f2d6-e26b81fca6f4.htm">
        <span data-tocFile="../toc/IDPGA.xml" class="icon toggle" onclick="ToggleExpandCollapse(this); return false;">
          <i class="fa fa-angle-right"> </i>
        </span>IConfiguration<wbr />Validity<wbr />Mask</a>
      <ul class="toc-menu is-hidden"> </ul>
    </li>
    <li>
      <a id="872d32cb-c2aa-8544-4c81-53feb0996348" class="has-submenu" href="872d32cb-c2aa-8544-4c81-53feb0996348.htm">
        <span data-tocFile="../toc/IDQGA.xml" class="icon toggle" onclick="ToggleExpandCollapse(this); return false;">
          <i class="fa fa-angle-right"> </i>
        </span>IJson<wbr />Conf<wbr />Editor<wbr />Attr</a>
      <ul class="toc-menu is-hidden"> </ul>
    </li>
    <li>
      <a id="8d5bae3e-b625-13a4-3481-fb279d8fa8f3" class="has-submenu" href="8d5bae3e-b625-13a4-3481-fb279d8fa8f3.htm">
        <span data-tocFile="../toc/IDRGA.xml" class="icon toggle" onclick="ToggleExpandCollapse(this); return false;">
          <i class="fa fa-angle-right"> </i>
        </span>ILicensed<wbr />Application</a>
      <ul class="toc-menu is-hidden"> </ul>
    </li>
    <li>
      <a id="1bfb8410-9aeb-5951-75cc-a2fda1cb5c87" class="has-submenu" href="1bfb8410-9aeb-5951-75cc-a2fda1cb5c87.htm">
        <span data-tocFile="../toc/IDSGA.xml" class="icon toggle" onclick="ToggleExpandCollapse(this); return false;">
          <i class="fa fa-angle-right"> </i>
        </span>ILicense<wbr />Decoder</a>
      <ul class="toc-menu is-hidden"> </ul>
    </li>
    <li>
      <a id="2ee63d93-297e-20b8-22b7-3e1065f2d0aa" class="has-submenu" href="2ee63d93-297e-20b8-22b7-3e1065f2d0aa.htm">
        <span data-tocFile="../toc/IDTGA.xml" class="icon toggle" onclick="ToggleExpandCollapse(this); return false;">
          <i class="fa fa-angle-right"> </i>
        </span>ILicensing<wbr />Support&lt;License<wbr />Type&gt;</a>
      <ul class="toc-menu is-hidden"> </ul>
    </li>
    <li>
      <a id="a7a96b87-323e-cdc1-64cd-e887bbc30ce1" class="has-submenu" href="a7a96b87-323e-cdc1-64cd-e887bbc30ce1.htm">
        <span data-tocFile="../toc/IDUGA.xml" class="icon toggle" onclick="ToggleExpandCollapse(this); return false;">
          <i class="fa fa-angle-right"> </i>
        </span>IMetadata<wbr />Structure<wbr />Validator</a>
      <ul class="toc-menu is-hidden"> </ul>
    </li>
    <li>
      <a id="7eb93f2f-79cf-bc02-2599-1ee92df670e8" class="has-submenu" href="7eb93f2f-79cf-bc02-2599-1ee92df670e8.htm">
        <span data-tocFile="../toc/IDVGA.xml" class="icon toggle" onclick="ToggleExpandCollapse(this); return false;">
          <i class="fa fa-angle-right"> </i>
        </span>ISchema<wbr />Member<wbr />Control<wbr />Attribute</a>
      <ul class="toc-menu is-hidden"> </ul>
    </li>
    <li>
      <a id="63c85198-8d75-b953-78c2-9dcf19beae0d" class="has-submenu" href="63c85198-8d75-b953-78c2-9dcf19beae0d.htm">
        <span data-tocFile="../toc/IDWGA.xml" class="icon toggle" onclick="ToggleExpandCollapse(this); return false;">
          <i class="fa fa-angle-right"> </i>
        </span>Json<wbr />Conf<wbr />Bit<wbr />Flag<wbr />Labels<wbr />Attribute</a>
      <ul class="toc-menu is-hidden"> </ul>
    </li>
    <li>
      <a id="c4d72f96-6f8d-d980-192d-f87016e301ec" class="has-submenu" href="c4d72f96-6f8d-d980-192d-f87016e301ec.htm">
        <span data-tocFile="../toc/IDXGA.xml" class="icon toggle" onclick="ToggleExpandCollapse(this); return false;">
          <i class="fa fa-angle-right"> </i>
        </span>Json<wbr />Conf<wbr />Editor<wbr />Attribute</a>
      <ul class="toc-menu is-hidden"> </ul>
    </li>
    <li>
      <a id="58df9712-0a5b-12ee-4450-5ab357a6ee1c" class="has-submenu" href="58df9712-0a5b-12ee-4450-5ab357a6ee1c.htm">
        <span data-tocFile="../toc/IDYGA.xml" class="icon toggle" onclick="ToggleExpandCollapse(this); return false;">
          <i class="fa fa-angle-right"> </i>
        </span>Json<wbr />Conf<wbr />Flag<wbr />Converter</a>
      <ul class="toc-menu is-hidden"> </ul>
    </li>
    <li>
      <a id="0757a61e-aecb-cd25-1445-0e968d8074b5" class="has-submenu" href="0757a61e-aecb-cd25-1445-0e968d8074b5.htm">
        <span data-tocFile="../toc/IDZGA.xml" class="icon toggle" onclick="ToggleExpandCollapse(this); return false;">
          <i class="fa fa-angle-right"> </i>
        </span>Json<wbr />Conf<wbr />Float<wbr />Editor<wbr />Attribute</a>
      <ul class="toc-menu is-hidden"> </ul>
    </li>
    <li>
      <a id="2e618ca6-ec6b-5ae3-59bb-7e1eda318307" class="has-submenu" href="2e618ca6-ec6b-5ae3-59bb-7e1eda318307.htm">
        <span data-tocFile="../toc/ID1GA.xml" class="icon toggle" onclick="ToggleExpandCollapse(this); return false;">
          <i class="fa fa-angle-right"> </i>
        </span>Json<wbr />Conf<wbr />Integer<wbr />Editor<wbr />Attribute</a>
      <ul class="toc-menu is-hidden"> </ul>
    </li>
    <li>
      <a id="87286e12-5aed-5c3f-894a-7978b2184e51" class="has-submenu" href="87286e12-5aed-5c3f-894a-7978b2184e51.htm">
        <span data-tocFile="../toc/ID2GA.xml" class="icon toggle" onclick="ToggleExpandCollapse(this); return false;">
          <i class="fa fa-angle-right"> </i>
        </span>Json<wbr />Conf<wbr />Search<wbr />Conditions<wbr />JAEditor<wbr />Attribute</a>
      <ul class="toc-menu is-hidden"> </ul>
    </li>
    <li>
      <a id="f29c2fec-efec-0a82-b351-a3a15252ed9b" class="has-submenu" href="f29c2fec-efec-0a82-b351-a3a15252ed9b.htm">
        <span data-tocFile="../toc/ID3GA.xml" class="icon toggle" onclick="ToggleExpandCollapse(this); return false;">
          <i class="fa fa-angle-right"> </i>
        </span>License<wbr />Content<wbr />Base</a>
      <ul class="toc-menu is-hidden"> </ul>
    </li>
    <li>
      <a id="bb5efd00-ad70-9514-92ed-6fbbf7e1d1b0" class="has-submenu" href="bb5efd00-ad70-9514-92ed-6fbbf7e1d1b0.htm">
        <span data-tocFile="../toc/ID4GA.xml" class="icon toggle" onclick="ToggleExpandCollapse(this); return false;">
          <i class="fa fa-angle-right"> </i>
        </span>License<wbr />Decoder</a>
      <ul class="toc-menu is-hidden"> </ul>
    </li>
    <li>
      <a id="f806c45c-dccd-97d1-7981-70860a25cef2" href="f806c45c-dccd-97d1-7981-70860a25cef2.htm">License<wbr />Decoder.<wbr />Enc<wbr />Mode</a>
    </li>
    <li>
      <a id="c70fbc56-39e8-68df-02f5-e84b61405d71" class="has-submenu" href="c70fbc56-39e8-68df-02f5-e84b61405d71.htm">
        <span data-tocFile="../toc/ID6GA.xml" class="icon toggle" onclick="ToggleExpandCollapse(this); return false;">
          <i class="fa fa-angle-right"> </i>
        </span>Metadata<wbr />Structure<wbr />Validator</a>
      <ul class="toc-menu is-hidden"> </ul>
    </li>
    <li>
      <a id="22664f96-97ef-2af5-2d5b-d3843161b901" class="has-submenu" href="22664f96-97ef-2af5-2d5b-d3843161b901.htm">
        <span data-tocFile="../toc/ID0AB0GA.xml" class="icon toggle" onclick="ToggleExpandCollapse(this); return false;">
          <i class="fa fa-angle-right"> </i>
        </span>Metadata<wbr />Structure<wbr />Validator.<wbr />Reference<wbr />Equality<wbr />Comparer</a>
      <ul class="toc-menu is-hidden"> </ul>
    </li>
    <li>
      <a id="174a41ba-3a24-b7a8-d670-7ac32cb9b81b" class="has-submenu" href="174a41ba-3a24-b7a8-d670-7ac32cb9b81b.htm">
        <span data-tocFile="../toc/ID0BB0GA.xml" class="icon toggle" onclick="ToggleExpandCollapse(this); return false;">
          <i class="fa fa-angle-right"> </i>
        </span>Metadata<wbr />Structure<wbr />Validator.<wbr />Temporary<wbr />Configuration</a>
      <ul class="toc-menu is-hidden"> </ul>
    </li>
    <li>
      <a id="0a181529-5bcd-019e-7c92-3e1db35712a4" class="has-submenu" href="0a181529-5bcd-019e-7c92-3e1db35712a4.htm">
        <span data-tocFile="../toc/ID0CB0GA.xml" class="icon toggle" onclick="ToggleExpandCollapse(this); return false;">
          <i class="fa fa-angle-right"> </i>
        </span>MFAssociated<wbr />Property<wbr />Attribute</a>
      <ul class="toc-menu is-hidden"> </ul>
    </li>
    <li>
      <a id="a52ceda7-4d4f-7ae1-90b4-3e1404090fab" href="a52ceda7-4d4f-7ae1-90b4-3e1404090fab.htm">MFAssociated<wbr />Property<wbr />Attribute.<wbr />Required<wbr />State</a>
    </li>
    <li>
      <a id="fe22c6a5-9339-3147-a2b8-5d2147be93a1" class="has-submenu" href="fe22c6a5-9339-3147-a2b8-5d2147be93a1.htm">
        <span data-tocFile="../toc/ID0EB0GA.xml" class="icon toggle" onclick="ToggleExpandCollapse(this); return false;">
          <i class="fa fa-angle-right"> </i>
        </span>MFClass<wbr />Attribute</a>
      <ul class="toc-menu is-hidden"> </ul>
    </li>
    <li>
      <a id="7dae6452-5880-5d27-bf91-ddee8f7be239" class="has-submenu" href="7dae6452-5880-5d27-bf91-ddee8f7be239.htm">
        <span data-tocFile="../toc/ID0FB0GA.xml" class="icon toggle" onclick="ToggleExpandCollapse(this); return false;">
          <i class="fa fa-angle-right"> </i>
        </span>MFClass<wbr />Group<wbr />Attribute</a>
      <ul class="toc-menu is-hidden"> </ul>
    </li>
    <li>
      <a id="9d52d4f6-d4b4-38b8-1718-32528e1e0659" class="has-submenu" href="9d52d4f6-d4b4-38b8-1718-32528e1e0659.htm">
        <span data-tocFile="../toc/ID0GB0GA.xml" class="icon toggle" onclick="ToggleExpandCollapse(this); return false;">
          <i class="fa fa-angle-right"> </i>
        </span>MFDeprecated<wbr />Attribute</a>
      <ul class="toc-menu is-hidden"> </ul>
    </li>
    <li>
      <a id="19e75645-b7a2-4757-eb32-76c33f80442b" class="has-submenu" href="19e75645-b7a2-4757-eb32-76c33f80442b.htm">
        <span data-tocFile="../toc/ID0HB0GA.xml" class="icon toggle" onclick="ToggleExpandCollapse(this); return false;">
          <i class="fa fa-angle-right"> </i>
        </span>MFIdentifier</a>
      <ul class="toc-menu is-hidden"> </ul>
    </li>
    <li>
      <a id="7e76e6b8-9fb1-b999-21d6-84c69d819c65" href="7e76e6b8-9fb1-b999-21d6-84c69d819c65.htm">MFIdentifier.<wbr />Set<wbr />As<wbr />Type</a>
    </li>
    <li>
      <a id="fe111054-2e64-58db-0e4e-72fea574b360" class="has-submenu" href="fe111054-2e64-58db-0e4e-72fea574b360.htm">
        <span data-tocFile="../toc/ID0JB0GA.xml" class="icon toggle" onclick="ToggleExpandCollapse(this); return false;">
          <i class="fa fa-angle-right"> </i>
        </span>MFIdentifier<wbr />Format<wbr />Constants</a>
      <ul class="toc-menu is-hidden"> </ul>
    </li>
    <li>
      <a id="9db657c9-f4a3-70c3-905d-581b3d6948d9" class="has-submenu" href="9db657c9-f4a3-70c3-905d-581b3d6948d9.htm">
        <span data-tocFile="../toc/ID0KB0GA.xml" class="icon toggle" onclick="ToggleExpandCollapse(this); return false;">
          <i class="fa fa-angle-right"> </i>
        </span>MFIdentifier<wbr />Json<wbr />Converter</a>
      <ul class="toc-menu is-hidden"> </ul>
    </li>
    <li>
      <a id="2832de92-ffa2-73e5-b498-f4806279eebf" class="has-submenu" href="2832de92-ffa2-73e5-b498-f4806279eebf.htm">
        <span data-tocFile="../toc/ID0LB0GA.xml" class="icon toggle" onclick="ToggleExpandCollapse(this); return false;">
          <i class="fa fa-angle-right"> </i>
        </span>MFNamed<wbr />ACLAttribute</a>
      <ul class="toc-menu is-hidden"> </ul>
    </li>
    <li>
      <a id="2393c6e4-a882-d796-80fc-c54a8b41b053" class="has-submenu" href="2393c6e4-a882-d796-80fc-c54a8b41b053.htm">
        <span data-tocFile="../toc/ID0MB0GA.xml" class="icon toggle" onclick="ToggleExpandCollapse(this); return false;">
          <i class="fa fa-angle-right"> </i>
        </span>MFObject<wbr />Attribute</a>
      <ul class="toc-menu is-hidden"> </ul>
    </li>
    <li>
      <a id="2bb93192-67f4-1480-b800-301c272db48e" class="has-submenu" href="2bb93192-67f4-1480-b800-301c272db48e.htm">
        <span data-tocFile="../toc/ID0NB0GA.xml" class="icon toggle" onclick="ToggleExpandCollapse(this); return false;">
          <i class="fa fa-angle-right"> </i>
        </span>MFObj<wbr />Type<wbr />Attribute</a>
      <ul class="toc-menu is-hidden"> </ul>
    </li>
    <li>
      <a id="45d574e8-f44b-bf50-226c-15bd2fda7a90" class="has-submenu" href="45d574e8-f44b-bf50-226c-15bd2fda7a90.htm">
        <span data-tocFile="../toc/ID0OB0GA.xml" class="icon toggle" onclick="ToggleExpandCollapse(this); return false;">
          <i class="fa fa-angle-right"> </i>
        </span>MFProperty<wbr />Def<wbr />Attribute</a>
      <ul class="toc-menu is-hidden"> </ul>
    </li>
    <li>
      <a id="793ae6c4-9f51-2152-96f2-3faa3284a354" class="has-submenu" href="793ae6c4-9f51-2152-96f2-3faa3284a354.htm">
        <span data-tocFile="../toc/ID0PB0GA.xml" class="icon toggle" onclick="ToggleExpandCollapse(this); return false;">
          <i class="fa fa-angle-right"> </i>
        </span>MFProperty<wbr />Def<wbr />Reference<wbr />Attribute</a>
      <ul class="toc-menu is-hidden"> </ul>
    </li>
    <li>
      <a id="d5ec93dd-8b2e-9c1d-ea3f-bea879be29bd" class="has-submenu" href="d5ec93dd-8b2e-9c1d-ea3f-bea879be29bd.htm">
        <span data-tocFile="../toc/ID0QB0GA.xml" class="icon toggle" onclick="ToggleExpandCollapse(this); return false;">
          <i class="fa fa-angle-right"> </i>
        </span>MFSkip<wbr />Attribute</a>
      <ul class="toc-menu is-hidden"> </ul>
    </li>
    <li>
      <a id="d08e5c4c-2818-e605-56df-903ffeec6e79" class="has-submenu" href="d08e5c4c-2818-e605-56df-903ffeec6e79.htm">
        <span data-tocFile="../toc/ID0RB0GA.xml" class="icon toggle" onclick="ToggleExpandCollapse(this); return false;">
          <i class="fa fa-angle-right"> </i>
        </span>MFState<wbr />Attribute</a>
      <ul class="toc-menu is-hidden"> </ul>
    </li>
    <li>
      <a id="94778619-fd53-1d66-6404-d9592f3a958e" class="has-submenu" href="94778619-fd53-1d66-6404-d9592f3a958e.htm">
        <span data-tocFile="../toc/ID0SB0GA.xml" class="icon toggle" onclick="ToggleExpandCollapse(this); return false;">
          <i class="fa fa-angle-right"> </i>
        </span>MFState<wbr />Transition<wbr />Attribute</a>
      <ul class="toc-menu is-hidden"> </ul>
    </li>
    <li>
      <a id="69acaa6c-4633-66ab-1eb1-aa10232b3218" class="has-submenu" href="69acaa6c-4633-66ab-1eb1-aa10232b3218.htm">
        <span data-tocFile="../toc/ID0TB0GA.xml" class="icon toggle" onclick="ToggleExpandCollapse(this); return false;">
          <i class="fa fa-angle-right"> </i>
        </span>MFStructure<wbr />Reference<wbr />Attribute</a>
      <ul class="toc-menu is-hidden"> </ul>
    </li>
    <li>
      <a id="9166e94b-152a-70ed-ff07-69240b793868" href="9166e94b-152a-70ed-ff07-69240b793868.htm">MFStructure<wbr />Reference<wbr />Attribute.<wbr />MFStructure<wbr />Reference<wbr />Type</a>
    </li>
    <li>
      <a id="ff59e046-4886-140d-986d-68fad52dbaf0" class="has-submenu" href="ff59e046-4886-140d-986d-68fad52dbaf0.htm">
        <span data-tocFile="../toc/ID0VB0GA.xml" class="icon toggle" onclick="ToggleExpandCollapse(this); return false;">
          <i class="fa fa-angle-right"> </i>
        </span>MFSubstructure<wbr />Reference<wbr />Attribute</a>
      <ul class="toc-menu is-hidden"> </ul>
    </li>
    <li>
      <a id="fed6d85f-cc82-8bac-5962-cf65459c269e" class="has-submenu" href="fed6d85f-cc82-8bac-5962-cf65459c269e.htm">
        <span data-tocFile="../toc/ID0WB0GA.xml" class="icon toggle" onclick="ToggleExpandCollapse(this); return false;">
          <i class="fa fa-angle-right"> </i>
        </span>MFUser<wbr />Group<wbr />Attribute</a>
      <ul class="toc-menu is-hidden"> </ul>
    </li>
    <li>
      <a id="4a19df9d-0ed6-8da5-6879-ec2252806c19" class="has-submenu" href="4a19df9d-0ed6-8da5-6879-ec2252806c19.htm">
        <span data-tocFile="../toc/ID0XB0GA.xml" class="icon toggle" onclick="ToggleExpandCollapse(this); return false;">
          <i class="fa fa-angle-right"> </i>
        </span>MFValue<wbr />List<wbr />Attribute</a>
      <ul class="toc-menu is-hidden"> </ul>
    </li>
    <li>
      <a id="930fda84-1b58-6087-8577-e20cdea9e1d2" class="has-submenu" href="930fda84-1b58-6087-8577-e20cdea9e1d2.htm">
        <span data-tocFile="../toc/ID0YB0GA.xml" class="icon toggle" onclick="ToggleExpandCollapse(this); return false;">
          <i class="fa fa-angle-right"> </i>
        </span>MFValue<wbr />List<wbr />Item<wbr />Attribute</a>
      <ul class="toc-menu is-hidden"> </ul>
    </li>
    <li>
      <a id="d8ce9b0b-54f9-dd99-9b2e-6b6e969d0647" class="has-submenu" href="d8ce9b0b-54f9-dd99-9b2e-6b6e969d0647.htm">
        <span data-tocFile="../toc/ID0ZB0GA.xml" class="icon toggle" onclick="ToggleExpandCollapse(this); return false;">
          <i class="fa fa-angle-right"> </i>
        </span>MFView<wbr />Attribute</a>
      <ul class="toc-menu is-hidden"> </ul>
    </li>
    <li>
      <a id="a28c0779-93d4-f165-daac-b96b349fa216" class="has-submenu" href="a28c0779-93d4-f165-daac-b96b349fa216.htm">
        <span data-tocFile="../toc/ID01B0GA.xml" class="icon toggle" onclick="ToggleExpandCollapse(this); return false;">
          <i class="fa fa-angle-right"> </i>
        </span>MFWorkflow<wbr />Attribute</a>
      <ul class="toc-menu is-hidden"> </ul>
    </li>
    <li>
      <a id="17026e44-88ac-6f12-4007-2ababa214058" class="has-submenu" href="17026e44-88ac-6f12-4007-2ababa214058.htm">
        <span data-tocFile="../toc/ID02B0GA.xml" class="icon toggle" onclick="ToggleExpandCollapse(this); return false;">
          <i class="fa fa-angle-right"> </i>
        </span>Multiline<wbr />Text<wbr />Editor<wbr />Attribute</a>
      <ul class="toc-menu is-hidden"> </ul>
    </li>
    <li>
      <a id="0e69688d-69d6-260d-9d3e-a3b4a9a667d7" class="has-submenu" href="0e69688d-69d6-260d-9d3e-a3b4a9a667d7.htm">
        <span data-tocFile="../toc/ID03B0GA.xml" class="icon toggle" onclick="ToggleExpandCollapse(this); return false;">
          <i class="fa fa-angle-right"> </i>
        </span>Nvs<wbr />Resource<wbr />Editor<wbr />Attribute</a>
      <ul class="toc-menu is-hidden"> </ul>
    </li>
    <li>
      <a id="108a3d2f-f2bc-9144-f5f3-95860a0dc250" class="has-submenu" href="108a3d2f-f2bc-9144-f5f3-95860a0dc250.htm">
        <span data-tocFile="../toc/ID04B0GA.xml" class="icon toggle" onclick="ToggleExpandCollapse(this); return false;">
          <i class="fa fa-angle-right"> </i>
        </span>Object<wbr />Members<wbr />Attribute</a>
      <ul class="toc-menu is-hidden"> </ul>
    </li>
    <li>
      <a id="27382d6b-0d34-e4f4-304f-92c3bf3e2fbc" class="has-submenu" href="27382d6b-0d34-e4f4-304f-92c3bf3e2fbc.htm">
        <span data-tocFile="../toc/ID05B0GA.xml" class="icon toggle" onclick="ToggleExpandCollapse(this); return false;">
          <i class="fa fa-angle-right"> </i>
        </span>Previewable<wbr />Text<wbr />Editor<wbr />Attribute</a>
      <ul class="toc-menu is-hidden"> </ul>
    </li>
    <li>
      <a id="1ca7e01f-eef4-b4d7-723d-446241641e62" class="has-submenu" href="1ca7e01f-eef4-b4d7-723d-446241641e62.htm">
        <span data-tocFile="../toc/ID06B0GA.xml" class="icon toggle" onclick="ToggleExpandCollapse(this); return false;">
          <i class="fa fa-angle-right"> </i>
        </span>Property<wbr />Value<wbr />Setter</a>
      <ul class="toc-menu is-hidden"> </ul>
    </li>
    <li>
      <a id="b8ee11b6-aaa3-4eb1-5096-55405d1ad4fd" class="has-submenu" href="b8ee11b6-aaa3-4eb1-5096-55405d1ad4fd.htm">
        <span data-tocFile="../toc/ID0AC0GA.xml" class="icon toggle" onclick="ToggleExpandCollapse(this); return false;">
          <i class="fa fa-angle-right"> </i>
        </span>Property<wbr />Value<wbr />Setter&lt;TPlaceholders&gt;</a>
      <ul class="toc-menu is-hidden"> </ul>
    </li>
    <li>
      <a id="0b277b9b-92f9-c3a4-6cf4-3911b632c53f" class="has-submenu" href="0b277b9b-92f9-c3a4-6cf4-3911b632c53f.htm">
        <span data-tocFile="../toc/ID0BC0GA.xml" class="icon toggle" onclick="ToggleExpandCollapse(this); return false;">
          <i class="fa fa-angle-right"> </i>
        </span>Resource<wbr />Editor<wbr />Attribute</a>
      <ul class="toc-menu is-hidden"> </ul>
    </li>
    <li>
      <a id="156d5822-a8c2-54ee-8c83-84f67744e41c" class="has-submenu" href="156d5822-a8c2-54ee-8c83-84f67744e41c.htm">
        <span data-tocFile="../toc/ID0CC0GA.xml" class="icon toggle" onclick="ToggleExpandCollapse(this); return false;">
          <i class="fa fa-angle-right"> </i>
        </span>Resource<wbr />Marker</a>
      <ul class="toc-menu is-hidden"> </ul>
    </li>
    <li>
      <a id="4797df83-a9a7-42ed-14da-49a680b95b13" class="has-submenu" href="4797df83-a9a7-42ed-14da-49a680b95b13.htm">
        <span data-tocFile="../toc/ID0DC0GA.xml" class="icon toggle" onclick="ToggleExpandCollapse(this); return false;">
          <i class="fa fa-angle-right"> </i>
        </span>Secure<wbr />Configuration<wbr />Manager&lt;TConfig&gt;</a>
      <ul class="toc-menu is-hidden"> </ul>
    </li>
    <li>
      <a id="bf3c9835-8f0c-5efd-605d-50f18e49ead7" class="has-submenu" href="bf3c9835-8f0c-5efd-605d-50f18e49ead7.htm">
        <span data-tocFile="../toc/ID0EC0GA.xml" class="icon toggle" onclick="ToggleExpandCollapse(this); return false;">
          <i class="fa fa-angle-right"> </i>
        </span>Security<wbr />Attribute</a>
      <ul class="toc-menu is-hidden"> </ul>
    </li>
    <li>
      <a id="7c66ff53-82dd-c021-d294-f24a828f423b" href="7c66ff53-82dd-c021-d294-f24a828f423b.htm">Security<wbr />Attribute.<wbr />User<wbr />Level</a>
    </li>
    <li>
      <a id="4be9bcb2-13b2-4e61-9dc3-74e1eb0babb0" class="has-submenu" href="4be9bcb2-13b2-4e61-9dc3-74e1eb0babb0.htm">
        <span data-tocFile="../toc/ID0GC0GA.xml" class="icon toggle" onclick="ToggleExpandCollapse(this); return false;">
          <i class="fa fa-angle-right"> </i>
        </span>Security<wbr />Settings&lt;TConfig&gt;</a>
      <ul class="toc-menu is-hidden"> </ul>
    </li>
    <li>
      <a id="9b155f44-8672-63c8-f557-629cb5756c5a" class="has-submenu" href="9b155f44-8672-63c8-f557-629cb5756c5a.htm">
        <span data-tocFile="../toc/ID0HC0GA.xml" class="icon toggle" onclick="ToggleExpandCollapse(this); return false;">
          <i class="fa fa-angle-right"> </i>
        </span>Term<wbr />Options<wbr />Editor<wbr />Attribute</a>
      <ul class="toc-menu is-hidden"> </ul>
    </li>
    <li>
      <a id="db888204-0666-a908-5ebc-76f2d4596acc" class="has-submenu" href="db888204-0666-a908-5ebc-76f2d4596acc.htm">
        <span data-tocFile="../toc/ID0IC0GA.xml" class="icon toggle" onclick="ToggleExpandCollapse(this); return false;">
          <i class="fa fa-angle-right"> </i>
        </span>Text<wbr />Editor<wbr />Attribute</a>
      <ul class="toc-menu is-hidden"> </ul>
    </li>
    <li>
      <a id="098ac8b9-3baf-b68e-7872-18cc76e08d1c" class="has-submenu" href="098ac8b9-3baf-b68e-7872-18cc76e08d1c.htm">
        <span data-tocFile="../toc/ID0JC0GA.xml" class="icon toggle" onclick="ToggleExpandCollapse(this); return false;">
          <i class="fa fa-angle-right"> </i>
        </span>Translatable<wbr />Content</a>
      <ul class="toc-menu is-hidden"> </ul>
    </li>
    <li>
      <a id="9ba270ee-905c-9702-a11d-aaa8ed021153" class="has-submenu" href="9ba270ee-905c-9702-a11d-aaa8ed021153.htm">
        <span data-tocFile="../toc/ID0KC0GA.xml" class="icon toggle" onclick="ToggleExpandCollapse(this); return false;">
          <i class="fa fa-angle-right"> </i>
        </span>Translatable<wbr />Content<wbr />Json<wbr />Converter</a>
      <ul class="toc-menu is-hidden"> </ul>
    </li>
    <li>
      <a id="a17328b1-36a1-5f5e-687f-17a0fd32918d" class="has-submenu" href="a17328b1-36a1-5f5e-687f-17a0fd32918d.htm">
        <span data-tocFile="../toc/ID0LC0GA.xml" class="icon toggle" onclick="ToggleExpandCollapse(this); return false;">
          <i class="fa fa-angle-right"> </i>
        </span>Translatable<wbr />Value</a>
      <ul class="toc-menu is-hidden"> </ul>
    </li>
    <li>
      <a id="0a4d4f04-595b-0c86-bee7-264e7d47381c" class="has-submenu" href="0a4d4f04-595b-0c86-bee7-264e7d47381c.htm">
        <span data-tocFile="../toc/ID0MC0GA.xml" class="icon toggle" onclick="ToggleExpandCollapse(this); return false;">
          <i class="fa fa-angle-right"> </i>
        </span>Typed<wbr />Value<wbr />Setter</a>
      <ul class="toc-menu is-hidden"> </ul>
    </li>
    <li>
      <a id="40847289-c506-c68e-ed0f-92c457eabcc3" class="has-submenu" href="40847289-c506-c68e-ed0f-92c457eabcc3.htm">
        <span data-tocFile="../toc/ID0NC0GA.xml" class="icon toggle" onclick="ToggleExpandCollapse(this); return false;">
          <i class="fa fa-angle-right"> </i>
        </span>Typed<wbr />Value<wbr />Setter&lt;TPlaceholders&gt;</a>
      <ul class="toc-menu is-hidden"> </ul>
    </li>
    <li>
      <a id="42537c2c-a883-b923-f68a-78ec76209f89" href="42537c2c-a883-b923-f68a-78ec76209f89.htm">Typed<wbr />Value<wbr />Setting<wbr />Mode</a>
    </li>
    <li>
      <a id="47094d27-5115-8d3a-0ead-45f954b88246" class="has-submenu" href="47094d27-5115-8d3a-0ead-45f954b88246.htm">
        <span data-tocFile="../toc/ID0PC0GA.xml" class="icon toggle" onclick="ToggleExpandCollapse(this); return false;">
          <i class="fa fa-angle-right"> </i>
        </span>Validation<wbr />Finding</a>
      <ul class="toc-menu is-hidden"> </ul>
    </li>
    <li>
      <a id="1df62d11-2b60-eeb7-1fcc-1316bbd8cffe" href="1df62d11-2b60-eeb7-1fcc-1316bbd8cffe.htm">Validation<wbr />Finding<wbr />Type</a>
    </li>
    <li>
      <a id="dc76f80c-c08d-230e-c686-d7ee83cec661" class="has-submenu" href="dc76f80c-c08d-230e-c686-d7ee83cec661.htm">
        <span data-tocFile="../toc/ID0RC0GA.xml" class="icon toggle" onclick="ToggleExpandCollapse(this); return false;">
          <i class="fa fa-angle-right"> </i>
        </span>Validation<wbr />Interrupted<wbr />Exception</a>
      <ul class="toc-menu is-hidden"> </ul>
    </li>
    <li>
      <a id="e258c824-b43f-e8c3-ce80-5c87778b7b55" class="has-submenu" href="e258c824-b43f-e8c3-ce80-5c87778b7b55.htm">
        <span data-tocFile="../toc/ID0SC0GA.xml" class="icon toggle" onclick="ToggleExpandCollapse(this); return false;">
          <i class="fa fa-angle-right"> </i>
        </span>Validation<wbr />Result<wbr />Base</a>
      <ul class="toc-menu is-hidden"> </ul>
    </li>
    <li>
      <a id="ce02aa51-d7db-1f30-2c41-60a188e1f5db" class="has-submenu" href="ce02aa51-d7db-1f30-2c41-60a188e1f5db.htm">
        <span data-tocFile="../toc/ID0TC0GA.xml" class="icon toggle" onclick="ToggleExpandCollapse(this); return false;">
          <i class="fa fa-angle-right"> </i>
        </span>Validation<wbr />Result<wbr />For<wbr />Upgrade</a>
      <ul class="toc-menu is-hidden"> </ul>
    </li>
    <li>
      <a id="aa548233-8c00-ee69-5acc-fb42f1943b1d" class="has-submenu" href="aa548233-8c00-ee69-5acc-fb42f1943b1d.htm">
        <span data-tocFile="../toc/ID0UC0GA.xml" class="icon toggle" onclick="ToggleExpandCollapse(this); return false;">
          <i class="fa fa-angle-right"> </i>
        </span>Validation<wbr />Result<wbr />For<wbr />Upgrade.<wbr />Metadata<wbr />Item<wbr />Params</a>
      <ul class="toc-menu is-hidden"> </ul>
    </li>
    <li>
      <a id="982ed90e-49bd-ccdf-e074-51c594cdf2e7" class="has-submenu" href="982ed90e-49bd-ccdf-e074-51c594cdf2e7.htm">
        <span data-tocFile="../toc/ID0VC0GA.xml" class="icon toggle" onclick="ToggleExpandCollapse(this); return false;">
          <i class="fa fa-angle-right"> </i>
        </span>Validation<wbr />Result<wbr />For<wbr />Validation</a>
      <ul class="toc-menu is-hidden"> </ul>
    </li>
    <li>
      <a id="f6ca438f-a180-448c-edd8-b6d2c1342a7f" class="has-submenu" href="f6ca438f-a180-448c-edd8-b6d2c1342a7f.htm">
        <span data-tocFile="../toc/ID0WC0GA.xml" class="icon toggle" onclick="ToggleExpandCollapse(this); return false;">
          <i class="fa fa-angle-right"> </i>
        </span>Validation<wbr />Result<wbr />For<wbr />Validation.<wbr />Detail<wbr />Item</a>
      <ul class="toc-menu is-hidden"> </ul>
    </li>
    <li>
      <a id="91d39670-9c11-3a75-aa53-2c6f3edb03b3" class="has-submenu" href="91d39670-9c11-3a75-aa53-2c6f3edb03b3.htm">
        <span data-tocFile="../toc/ID0XC0GA.xml" class="icon toggle" onclick="ToggleExpandCollapse(this); return false;">
          <i class="fa fa-angle-right"> </i>
        </span>Validation<wbr />Result<wbr />For<wbr />Validation.<wbr />Results</a>
      <ul class="toc-menu is-hidden"> </ul>
    </li>
    <li>
      <a id="daf81bb5-e28f-3398-4f09-ee1996526700" class="has-submenu" href="daf81bb5-e28f-3398-4f09-ee1996526700.htm">
        <span data-tocFile="../toc/ID0YC0GA.xml" class="icon toggle" onclick="ToggleExpandCollapse(this); return false;">
          <i class="fa fa-angle-right"> </i>
        </span>Validation<wbr />Result<wbr />For<wbr />Validation.<wbr />Summary<wbr />Module</a>
      <ul class="toc-menu is-hidden"> </ul>
    </li>
    <li>
      <a id="65abf787-f88d-0b55-8743-4d25aeb060e8" class="has-submenu" href="65abf787-f88d-0b55-8743-4d25aeb060e8.htm">
        <span data-tocFile="../toc/ID0ZC0GA.xml" class="icon toggle" onclick="ToggleExpandCollapse(this); return false;">
          <i class="fa fa-angle-right"> </i>
        </span>Value<wbr />Options<wbr />Attribute</a>
      <ul class="toc-menu is-hidden"> </ul>
    </li>
    <li>
      <a id="ce56b65d-784d-596b-7a49-c7bf1c80a1df" class="has-submenu" href="ce56b65d-784d-596b-7a49-c7bf1c80a1df.htm">
        <span data-tocFile="../toc/ID01C0GA.xml" class="icon toggle" onclick="ToggleExpandCollapse(this); return false;">
          <i class="fa fa-angle-right"> </i>
        </span>Value<wbr />Setter<wbr />Attribute</a>
      <ul class="toc-menu is-hidden"> </ul>
    </li>
    <li>
      <a id="c4dffecd-4447-f333-9335-33da1f74ab3d" class="has-submenu" href="c4dffecd-4447-f333-9335-33da1f74ab3d.htm">
        <span data-tocFile="../toc/ID02C0GA.xml" class="icon toggle" onclick="ToggleExpandCollapse(this); return false;">
          <i class="fa fa-angle-right"> </i>
        </span>Vault<wbr />Element<wbr />Reference<wbr />Attribute</a>
      <ul class="toc-menu is-hidden"> </ul>
    </li>
  </tocItems>
</toc>