<?xml version="1.0" encoding="utf-8"?>
<toc>
  <breadcrumbs>
    <li>
      <a href="854ccd60-6c3b-4754-1fee-cd46e85c309b.htm">Docs</a>
    </li>
    <li>
      <a href="854ccd60-6c3b-4754-1fee-cd46e85c309b.htm">Namespaces</a>
    </li>
    <li>
      <a href="561f7c2b-6a74-0008-6288-36e80455f9d4.htm">MFiles.<wbr />VAF Namespaces</a>
    </li>
    <li>
      <a href="5a079801-0cdc-4fb9-e9e1-a77870477d9f.htm">MFiles.<wbr />VAF.<wbr />Configuration Namespaces</a>
    </li>
    <li>
      <a href="6cd7a669-d464-de8d-d6f5-9c56ea2c5728.htm">MFiles.<wbr />VAF.<wbr />Configuration.<wbr />Logging.<wbr />Sensitivity<wbr />Filters</a>
    </li>
    <li>
      <a href="b3168161-fb7b-8234-acb9-84b969a2132e.htm">Object<wbr />Version<wbr />Log<wbr />Sensitivity<wbr />Filter</a>
    </li>
  </breadcrumbs>
  <tocItems>
    <li>
      <a id="bb78cda1-3921-866c-2523-87b43b754bb6" href="bb78cda1-3921-866c-2523-87b43b754bb6.htm">Constructor</a>
    </li>
    <li>
      <a id="b5732469-8b78-fc61-cfd0-31d231089829" href="b5732469-8b78-fc61-cfd0-31d231089829.htm">Properties</a>
    </li>
    <li>
      <a id="3f67952f-98d1-7d32-7ba5-0e905e083bb9" class="has-submenu" href="3f67952f-98d1-7d32-7ba5-0e905e083bb9.htm">
        <span data-tocFile="../toc/IDCKQEBA.xml" class="icon toggle" onclick="ToggleExpandCollapse(this); return false;">
          <i class="fa fa-angle-right"> </i>
        </span>Methods</a>
      <ul class="toc-menu is-hidden"> </ul>
    </li>
  </tocItems>
</toc>